{
    "updated_at": "2026-07-14 08:50:31",
    "list": [
        {
            "ticker": "472150",
            "name": "TIGER 배당커버드콜액티브",
            "price": "20,985원",
            "dividend": "510원",
            "pay_times": "연 12회",
            "return_1y": "150.02%",
            "sort_rate": 150.02
        },
        {
            "ticker": "458730",
            "name": "TIGER 미국배당다우존스",
            "price": "15,495원",
            "dividend": "95원",
            "pay_times": "연 12회",
            "return_1y": "32.63%",
            "sort_rate": 32.63
        },
        {
            "ticker": "498400",
            "name": "KODEX 200타겟위클리커버드콜",
            "price": "20,870원",
            "dividend": "62원",
            "pay_times": "연 12회",
            "return_1y": "0.00%",
            "sort_rate": 0.0
        },
        {
            "ticker": "161510",
            "name": "PLUS 고배당주",
            "price": "24,875원",
            "dividend": "74원",
            "pay_times": "연 4회",
            "return_1y": "0.00%",
            "sort_rate": 0.0
        },
        {
            "ticker": "486290",
            "name": "TIGER 미국나스닥100타겟데일리커버드콜",
            "price": "11,690원",
            "dividend": "35원",
            "pay_times": "연 12회",
            "return_1y": "0.00%",
            "sort_rate": 0.0
        },
        {
            "ticker": "487230",
            "name": "KODEX 미국AI전력핵심인프라",
            "price": "23,690원",
            "dividend": "71원",
            "pay_times": "연 12회",
            "return_1y": "0.00%",
            "sort_rate": 0.0
        },
        {
            "ticker": "441640",
            "name": "KODEX 미국배당커버드콜액티브",
            "price": "13,380원",
            "dividend": "40원",
            "pay_times": "연 12회",
            "return_1y": "0.00%",
            "sort_rate": 0.0
        },
        {
            "ticker": "329200",
            "name": "TIGER 리츠부동산인프라",
            "price": "4,000원",
            "dividend": "12원",
            "pay_times": "연 12회",
            "return_1y": "0.00%",
            "sort_rate": 0.0
        },
        {
            "ticker": "446720",
            "name": "SOL 미국배당다우존스",
            "price": "14,210원",
            "dividend": "42원",
            "pay_times": "연 12회",
            "return_1y": "0.00%",
            "sort_rate": 0.0
        },
        {
            "ticker": "494300",
            "name": "KODEX 미국나스닥100데일리커버드콜OTM",
            "price": "10,230원",
            "dividend": "30원",
            "pay_times": "연 12회",
            "return_1y": "0.00%",
            "sort_rate": 0.0
        },
        {
            "ticker": "402970",
            "name": "ACE 미국배당다우존스",
            "price": "15,735원",
            "dividend": "47원",
            "pay_times": "연 12회",
            "return_1y": "0.00%",
            "sort_rate": 0.0
        },
        {
            "ticker": "498410",
            "name": "KODEX 금융고배당TOP10타겟위클리커버드콜",
            "price": "12,345원",
            "dividend": "37원",
            "pay_times": "연 12회",
            "return_1y": "0.00%",
            "sort_rate": 0.0
        },
        {
            "ticker": "466940",
            "name": "TIGER 은행고배당플러스TOP10",
            "price": "27,005원",
            "dividend": "81원",
            "pay_times": "연 12회",
            "return_1y": "0.00%",
            "sort_rate": 0.0
        },
        {
            "ticker": "476550",
            "name": "TIGER 미국30년국채커버드콜액티브(H)",
            "price": "7,045원",
            "dividend": "21원",
            "pay_times": "연 12회",
            "return_1y": "0.00%",
            "sort_rate": 0.0
        },
        {
            "ticker": "475720",
            "name": "RISE 200위클리커버드콜",
            "price": "12,925원",
            "dividend": "38원",
            "pay_times": "연 12회",
            "return_1y": "0.00%",
            "sort_rate": 0.0
        },
        {
            "ticker": "441800",
            "name": "TIME Korea플러스배당액티브",
            "price": "29,845원",
            "dividend": "89원",
            "pay_times": "연 12회",
            "return_1y": "0.00%",
            "sort_rate": 0.0
        },
        {
            "ticker": "490590",
            "name": "RISE 미국AI밸류체인데일리고정커버드콜",
            "price": "15,635원",
            "dividend": "46원",
            "pay_times": "연 12회",
            "return_1y": "0.00%",
            "sort_rate": 0.0
        },
        {
            "ticker": "0177R0",
            "name": "TIGER 반도체TOP10커버드콜액티브",
            "price": "11,715원",
            "dividend": "35원",
            "pay_times": "연 12회",
            "return_1y": "0.00%",
            "sort_rate": 0.0
        },
        {
            "ticker": "481060",
            "name": "KODEX 미국30년국채타겟커버드콜(합성 H)",
            "price": "7,575원",
            "dividend": "22원",
            "pay_times": "연 12회",
            "return_1y": "0.00%",
            "sort_rate": 0.0
        },
        {
            "ticker": "491010",
            "name": "TIGER 글로벌AI전력인프라액티브",
            "price": "30,410원",
            "dividend": "91원",
            "pay_times": "연 12회",
            "return_1y": "0.00%",
            "sort_rate": 0.0
        },
        {
            "ticker": "458760",
            "name": "TIGER 미국배당다우존스타겟커버드콜2호",
            "price": "11,475원",
            "dividend": "34원",
            "pay_times": "연 12회",
            "return_1y": "0.00%",
            "sort_rate": 0.0
        },
        {
            "ticker": "367760",
            "name": "RISE 네트워크인프라",
            "price": "58,260원",
            "dividend": "174원",
            "pay_times": "연 12회",
            "return_1y": "0.00%",
            "sort_rate": 0.0
        },
        {
            "ticker": "0167B0",
            "name": "SOL 200타겟위클리커버드콜",
            "price": "12,075원",
            "dividend": "36원",
            "pay_times": "연 12회",
            "return_1y": "0.00%",
            "sort_rate": 0.0
        },
        {
            "ticker": "482730",
            "name": "TIGER 미국S&P500타겟데일리커버드콜",
            "price": "12,785원",
            "dividend": "38원",
            "pay_times": "연 12회",
            "return_1y": "0.00%",
            "sort_rate": 0.0
        },
        {
            "ticker": "251600",
            "name": "PLUS 고배당주채권혼합",
            "price": "15,350원",
            "dividend": "46원",
            "pay_times": "연 4회",
            "return_1y": "0.00%",
            "sort_rate": 0.0
        },
        {
            "ticker": "489250",
            "name": "KODEX 미국배당다우존스",
            "price": "13,330원",
            "dividend": "39원",
            "pay_times": "연 12회",
            "return_1y": "0.00%",
            "sort_rate": 0.0
        },
        {
            "ticker": "0101N0",
            "name": "RISE AI전력인프라",
            "price": "18,655원",
            "dividend": "55원",
            "pay_times": "연 12회",
            "return_1y": "0.00%",
            "sort_rate": 0.0
        },
        {
            "ticker": "315960",
            "name": "RISE 대형고배당10TR",
            "price": "80,535원",
            "dividend": "241원",
            "pay_times": "연 12회",
            "return_1y": "0.00%",
            "sort_rate": 0.0
        },
        {
            "ticker": "0105E0",
            "name": "SOL 코리아고배당",
            "price": "12,985원",
            "dividend": "38원",
            "pay_times": "연 12회",
            "return_1y": "0.00%",
            "sort_rate": 0.0
        },
        {
            "ticker": "491620",
            "name": "RISE 미국테크100데일리고정커버드콜",
            "price": "11,530원",
            "dividend": "34원",
            "pay_times": "연 12회",
            "return_1y": "0.00%",
            "sort_rate": 0.0
        }
    ]
}